fakturuj/__init__.py
fakturuj/fakturuj.py
fakturuj/templates/invoice.html
fakturuj_pyco-1.3.dist-info/DESCRIPTION.rst
fakturuj_pyco-1.3.dist-info/METADATA
fakturuj_pyco-1.3.dist-info/RECORD
fakturuj_pyco-1.3.dist-info/WHEEL
fakturuj_pyco-1.3.dist-info/entry_points.txt
fakturuj_pyco-1.3.dist-info/metadata.json
fakturuj_pyco-1.3.dist-info/top_level.txt
